scriptgui/__init__.py
scriptgui/decorator.py
scriptgui/web.py
scriptgui-0.2.2.dist-info/entry_points.txt
scriptgui-0.2.2.dist-info/LICENSE.md
scriptgui-0.2.2.dist-info/METADATA
scriptgui-0.2.2.dist-info/WHEEL
scriptgui-0.2.2.dist-info/RECORD
