Metadata-Version: 2.1
Name: scriptgui
Version: 0.2.2
Summary: organize and interact with scripts via a plugin style pattern, using a browser based interface
Author: tyler jones
Requires-Python: >=3.7
Classifier: Programming Language :: Python :: 3
Classifier: Programming Language :: Python :: 3.7
Classifier: Programming Language :: Python :: 3.8
Classifier: Programming Language :: Python :: 3.9
Classifier: Programming Language :: Python :: 3.10
Classifier: Programming Language :: Python :: 3.11
Requires-Dist: fastapi (>=0.88.0,<0.89.0)
Requires-Dist: flask (==2.0.1)
Requires-Dist: idom[flask] (>=0.42.0,<0.43.0)
Requires-Dist: toml (>=0.10.2,<0.11.0)
Requires-Dist: uvicorn (>=0.20.0,<0.21.0)
